usps/__init__.py
usps/__main__.py
usps/storage.py
usps/timezones.py
usps/tracking/__init__.py
usps/tracking/ups.py
usps/tracking/usps.py
usps_cli-0.10.2.dist-info/METADATA
usps_cli-0.10.2.dist-info/WHEEL
usps_cli-0.10.2.dist-info/entry_points.txt
usps_cli-0.10.2.dist-info/licenses/LICENSE.txt
usps_cli-0.10.2.dist-info/RECORD
