Metadata-Version: 2.4
Name: usps-cli
Version: 0.10.2
Summary: A CLI for tracking packages from USPS.
Project-URL: Homepage, https://github.com/iiPythonx/usps
Project-URL: Issues, https://github.com/iiPythonx/usps/issues
Author-email: iiPython <ben@iipython.dev>
License-File: LICENSE.txt
Classifier: Development Status :: 4 - Beta
Classifier: Environment :: Console
Classifier: Intended Audience :: End Users/Desktop
Classifier: License :: OSI Approved :: MIT License
Classifier: Operating System :: OS Independent
Classifier: Programming Language :: Python :: 3
Classifier: Programming Language :: Python :: 3.10
Classifier: Programming Language :: Python :: 3.11
Classifier: Programming Language :: Python :: 3.12
Classifier: Programming Language :: Python :: 3.13
Classifier: Topic :: Internet
Classifier: Topic :: Utilities
Requires-Python: >=3.10
Requires-Dist: click>=8.1.7
Requires-Dist: requests>=2.32.3
Requires-Dist: rich>=13.8.1
Requires-Dist: selectolax>=0.3.26
Requires-Dist: selenium>=4.25.0
Requires-Dist: typer>=0.12.5
